cloudmesh_diagram-4.3.9-py3.8-nspkg.pth
cloudmesh/diagram/__init__.py
cloudmesh/diagram/__version__.py
cloudmesh/diagram/diagram.py
cloudmesh/diagram/command/__init__.py
cloudmesh/diagram/command/diagram.py
cloudmesh_diagram-4.3.9.dist-info/LICENSE
cloudmesh_diagram-4.3.9.dist-info/METADATA
cloudmesh_diagram-4.3.9.dist-info/WHEEL
cloudmesh_diagram-4.3.9.dist-info/namespace_packages.txt
cloudmesh_diagram-4.3.9.dist-info/top_level.txt
cloudmesh_diagram-4.3.9.dist-info/RECORD
